MANIFEST.in
setup.py
tbsh/__init__.py
tbsh.egg-info/PKG-INFO
tbsh.egg-info/SOURCES.txt
tbsh.egg-info/dependency_links.txt
tbsh.egg-info/requires.txt
tbsh.egg-info/top_level.txt