Metadata-Version: 1.0
Name: tbsh
Version: 0.3.6
Summary: The funniest joke in the world
Home-page: http://github.com/storborg/funniest
Author: Sriharsha Sammeta
Author-email: sriharsha4444@icloud.com
License: MIT
Platform: UNKNOWN
